tensorflow_checkpoint_reader/__init__.py
tensorflow_checkpoint_reader/bundle_reader.py
tensorflow_checkpoint_reader/core.py
tensorflow_checkpoint_reader/env.py
tensorflow_checkpoint_reader/env_time.py
tensorflow_checkpoint_reader/errors.py
tensorflow_checkpoint_reader/file_statistics.py
tensorflow_checkpoint_reader/file_system.py
tensorflow_checkpoint_reader/file_system_helper.py
tensorflow_checkpoint_reader/io.py
tensorflow_checkpoint_reader/iterator.py
tensorflow_checkpoint_reader/load_library.py
tensorflow_checkpoint_reader/misc.py
tensorflow_checkpoint_reader/naming.py
tensorflow_checkpoint_reader/numpy_util.py
tensorflow_checkpoint_reader/pb/tensorflow/compiler/jit/xla_activity.proto
tensorflow_checkpoint_reader/pb/tensorflow/compiler/jit/xla_activity_pb2.py
tensorflow_checkpoint_reader/pb/tensorflow/compiler/mlir/lite/quantization/quantization_info.proto
tensorflow_checkpoint_reader/pb/tensorflow/compiler/mlir/lite/quantization/quantization_info_pb2.py
tensorflow_checkpoint_reader/pb/tensorflow/compiler/tf2tensorrt/utils/trt_engine_instance.proto
tensorflow_checkpoint_reader/pb/tensorflow/compiler/tf2tensorrt/utils/trt_engine_instance_pb2.py
tensorflow_checkpoint_reader/pb/tensorflow/compiler/tf2xla/host_compute_metadata.proto
tensorflow_checkpoint_reader/pb/tensorflow/compiler/tf2xla/host_compute_metadata_pb2.py
tensorflow_checkpoint_reader/pb/tensorflow/compiler/tf2xla/tf2xla.proto
tensorflow_checkpoint_reader/pb/tensorflow/compiler/tf2xla/tf2xla_pb2.py
tensorflow_checkpoint_reader/pb/tensorflow/compiler/xla/pjrt/distributed/protocol.proto
tensorflow_checkpoint_reader/pb/tensorflow/compiler/xla/pjrt/distributed/protocol_pb2.py
tensorflow_checkpoint_reader/pb/tensorflow/compiler/xla/python/tpu_driver/tpu_driver.proto
tensorflow_checkpoint_reader/pb/tensorflow/compiler/xla/python/tpu_driver/tpu_driver_pb2.py
tensorflow_checkpoint_reader/pb/tensorflow/compiler/xla/python/tpu_driver/tpu_service.proto
tensorflow_checkpoint_reader-0.1.2.dist-info/LICENSE
tensorflow_checkpoint_reader-0.1.2.dist-info/WHEEL
tensorflow_checkpoint_reader-0.1.2.dist-info/METADATA
tensorflow_checkpoint_reader-0.1.2.dist-info/RECORD
